{
  "data": [
    {
      "title": "肌肤出色无需隐藏 童颜肌不用ZHUANG",
      "date": "2018.06.04-2018.06.18",
      "people": 1205,
      "num": 52,
      "sponsor": "pc小编_轻松小熊",
      "img": "assets/img/ac/a1.jpg",
      "content": "虽然已过了过六一儿童节的年龄，但是“老阿姨”们还是纷纷拿起手上的化妆工具，隐藏肌肤瑕疵，画上减龄妆，假装自己还是未成年少女，趁机装把嫩，怀念逝去的青春。"
    },
    {
      "title": "自然无瑕的天生好皮肤 阿玛尼红气垫",
      "date": "2018.06.04-2018.06.18",
      "people": 1205,
      "num": 52,
      "sponsor": "pc小编_轻松小熊",
      "img": "assets/img/ac/a2.jpg",
      "content": "小编是个懒人，所以化妆包里的常驻人口除了口红之外，可能就是那个出门在外的补妆好手——气垫了。毕竟平常用粉底液上妆可能需要花费三分钟，但是用气垫上妆，就只需要花大概30s的时间，而且它的光泽度普遍都很好！"
    },
    {
      "title": "明星们纷纷为TA打call的美肌神器 它到底有什么能",
      "date": "2018.06.04-2018.06.18",
      "people": 1205,
      "num": 52,
      "sponsor": "pc小编_轻松小熊",
      "img": "assets/img/ac/a3.jpg",
      "content": "无论在哪里，明星总能成大众视线的焦点。她们仿佛自己会发光一般，即便是在远处也依然光彩夺目，格外惹眼。她们不仅有让人羡慕的身材，更有让人嫉妒的肌肤。小编也和你们一样哦，看到她们白皙嫩滑的脸蛋，羡慕的口水都要流出来啦~明星们每天不是熬夜拍戏，就是在天上飞来飞去，但是无论什么时候出现在镜头前，不管带妆还是素颜，好皮肤总是永远在线！"
    },
    {
      "title": "清爽水润的沐浴时光 洗去一天的疲惫与烦恼",
      "date": "2018.06.04-2018.06.18",
      "people": 1205,
      "num": 52,
      "sponsor": "pc小编_轻松小熊",
      "img": "assets/img/ac/a4.jpg",
      "content": "夏天天气炎热，加上长期处于空调房中，肌肤容易缺失水分。。我们往往只注重保养脸部肌肤，却忽略了身体肌肤也需要用心呵护。使用清洁力太强的沐浴乳反而会伤害肌肤，导致皮肤更加干燥，出现瘙痒等症状，并容易导致皮肤提早老化。"
    },
    {
      "title": "地表超强遮瑕底妆 阿玛尼权力粉底液",
      "date": "2018.06.04-2018.06.18",
      "people": 1205,
      "num": 52,
      "sponsor": "pc小编_轻松小熊",
      "img": "assets/img/ac/a5.jpg",
      "content": "不知道大家平时化妆的时候，有没有遇到过这种窘境？脸上的瑕疵太多，痘印、斑纹、黑眼圈，甚至是严重爆痘……遮起来费功夫不说，而且还要用掉大半瓶的遮瑕粉底，一层又一层的粉底真的会让你的脸很假，不知道该如何是好！"
    },
    {
      "title": "保湿才是夏日的正确打开方式——碧欧泉「绿活泉」",
      "date": "2018.06.04-2018.06.18",
      "people": 1205,
      "num": 52,
      "sponsor": "pc小编_轻松小熊",
      "img": "assets/img/ac/a6.png",
      "content": "随着气温渐升，小仙女们已经充分感受到了夏日的热情似火~想要美美地过一“夏”，除了焕新衣橱以外，补水保湿的警钟也该是时候拉响啦！"
    },
    {
      "title": "一抹红唇提升时尚品味 阿玛尼小胖丁",
      "date": "2018.06.04-2018.06.18",
      "people": 1205,
      "num": 52,
      "sponsor": "pc小编_轻松小熊",
      "img": "assets/img/ac/a7.png",
      "content": "说起红唇，我们通常会想到的就是这几个关键词：女王、性感、成熟、美艳，或者是复古、冷酷、距离感、攻击性强。但是不得不承认的是，脸色不好、面容倦怠的时候，只要涂上一抹红唇，分分钟变身女王，似乎拥有了征服世界的勇气！"
    },
    {
      "title": "告别各种遮瑕烦恼 阿玛尼带来完美底妆G",
      "date": "2018.06.04-2018.06.18",
      "people": 1205,
      "num": 52,
      "sponsor": "pc小编_轻松小熊",
      "img": "assets/img/ac/a8.png",
      "content": "虽然已过了过六一儿童节的年龄，但是“老阿姨”们还是纷纷拿起手上的化妆工具，隐藏肌肤瑕疵，画上减龄妆，假装自己还是未成年少女，趁机装把嫩，怀念逝去的青春。"
    },
    {
      "title": "肌肤出色无需隐藏 童颜肌不用ZHUANG",
      "date": "2018.06.04-2018.06.18",
      "people": 1205,
      "num": 52,
      "sponsor": "pc小编_轻松小熊",
      "img": "assets/img/ac/a9.jpg",
      "content": "虽然已过了过六一儿童节的年龄，但是“老阿姨”们还是纷纷拿起手上的化妆工具，隐藏肌肤瑕疵，画上减龄妆，假装自己还是未成年少女，趁机装把嫩，怀念逝去的青春。"
    },
    {
      "title": "肌肤出色无需隐藏 童颜肌不用ZHUANG",
      "date": "2018.06.04-2018.06.18",
      "people": 1205,
      "num": 52,
      "sponsor": "pc小编_轻松小熊",
      "img": "assets/img/ac/a10.jpg",
      "content": "虽然已过了过六一儿童节的年龄，但是“老阿姨”们还是纷纷拿起手上的化妆工具，隐藏肌肤瑕疵，画上减龄妆，假装自己还是未成年少女，趁机装把嫩，怀念逝去的青春。"
    },
    {
      "title": "肌肤出色无需隐藏 童颜肌不用ZHUANG",
      "date": "2018.06.04-2018.06.18",
      "people": 1205,
      "num": 52,
      "sponsor": "pc小编_轻松小熊",
      "img": "assets/img/ac/a1.jpg",
      "content": "虽然已过了过六一儿童节的年龄，但是“老阿姨”们还是纷纷拿起手上的化妆工具，隐藏肌肤瑕疵，画上减龄妆，假装自己还是未成年少女，趁机装把嫩，怀念逝去的青春。"
    }
  ]
}
